RagPUREAI_extract/RagPUREAI_extract.cpython-312-x86_64-linux-gnu.so
RagPUREAI_extract/__init__.py
RagPUREAI_extract-0.1.3.dist-info/METADATA
RagPUREAI_extract-0.1.3.dist-info/WHEEL
RagPUREAI_extract-0.1.3.dist-info/top_level.txt
RagPUREAI_extract-0.1.3.dist-info/RECORD
